odoo10_addon_account_payment_mode-10.0.1.0.2-py2.7-nspkg.pth
odoo/addons/account_payment_mode/README.rst
odoo/addons/account_payment_mode/__init__.py
odoo/addons/account_payment_mode/__manifest__.py
odoo/addons/account_payment_mode/demo/payment_demo.xml
odoo/addons/account_payment_mode/i18n/am.po
odoo/addons/account_payment_mode/i18n/ca.po
odoo/addons/account_payment_mode/i18n/da_DK.po
odoo/addons/account_payment_mode/i18n/de.po
odoo/addons/account_payment_mode/i18n/el_GR.po
odoo/addons/account_payment_mode/i18n/es.po
odoo/addons/account_payment_mode/i18n/es_ES.po
odoo/addons/account_payment_mode/i18n/fi.po
odoo/addons/account_payment_mode/i18n/fr.po
odoo/addons/account_payment_mode/i18n/gl.po
odoo/addons/account_payment_mode/i18n/hr.po
odoo/addons/account_payment_mode/i18n/it.po
odoo/addons/account_payment_mode/i18n/nb_NO.po
odoo/addons/account_payment_mode/i18n/nl.po
odoo/addons/account_payment_mode/i18n/nl_NL.po
odoo/addons/account_payment_mode/i18n/pt.po
odoo/addons/account_payment_mode/i18n/pt_BR.po
odoo/addons/account_payment_mode/i18n/pt_PT.po
odoo/addons/account_payment_mode/i18n/sl.po
odoo/addons/account_payment_mode/i18n/tr.po
odoo/addons/account_payment_mode/migrations/10.0.1.0.2/pre-migration.py
odoo/addons/account_payment_mode/models/__init__.py
odoo/addons/account_payment_mode/models/account_journal.py
odoo/addons/account_payment_mode/models/account_payment_method.py
odoo/addons/account_payment_mode/models/account_payment_mode.py
odoo/addons/account_payment_mode/models/res_partner_bank.py
odoo/addons/account_payment_mode/security/account_payment_mode.xml
odoo/addons/account_payment_mode/security/ir.model.access.csv
odoo/addons/account_payment_mode/views/account_journal.xml
odoo/addons/account_payment_mode/views/account_payment_method.xml
odoo/addons/account_payment_mode/views/account_payment_mode.xml
odoo/addons/account_payment_mode/views/res_partner.xml
odoo/addons/account_payment_mode/views/res_partner_bank.xml
odoo10_addon_account_payment_mode-10.0.1.0.2.dist-info/DESCRIPTION.rst
odoo10_addon_account_payment_mode-10.0.1.0.2.dist-info/METADATA
odoo10_addon_account_payment_mode-10.0.1.0.2.dist-info/RECORD
odoo10_addon_account_payment_mode-10.0.1.0.2.dist-info/WHEEL
odoo10_addon_account_payment_mode-10.0.1.0.2.dist-info/metadata.json
odoo10_addon_account_payment_mode-10.0.1.0.2.dist-info/namespace_packages.txt
odoo10_addon_account_payment_mode-10.0.1.0.2.dist-info/top_level.txt
